[{"room":"Rm 3111, Lift 19, 22","until":22},{"room":"Rm 4160, Lift 33","until":8},{"room":"Rm 3209A","until":14},{"room":"Rm 3207, Lift 21","until":14},{"room":"Rm 4214, Lift 19 (52)","until":10},{"room":"G021, LSK Bldg","until":11},{"room":"Rm 3005, Lift 4","until":8},{"room":"Rm 3115, Lift 19, 22","until":10},{"room":"Rm 1026, LSK Bldg (24)","until":8},{"room":"Lecture Theater E (143)","until":14},{"room":"Rm 2014, CYT Bldg","until":12},{"room":"Rm 4381","until":17},{"room":"Rm 4504, Lift 25-26 (54)","until":8},{"room":"Rm 1511, Lift 27-28 (42)","until":8},{"room":"Lecture Theater F (134)","until":11},{"room":"Rm 5564, Lift 27-28 (30)","until":8},{"room":"G005, CYT Bldg (30)","until":11},{"room":"Rm 2209","until":14},{"room":"G005, LSK Bldg","until":8},{"room":"Multi-function Room, LG4, LIB","until":11},{"room":"Rm 2463, Lift 25-26 (42)","until":8},{"room":"Rm 5510, Lift 25-26 (30)","until":11},{"room":"Rm 5562, Lift 27-28 (30)","until":8},{"room":"Rm 1505, Lift 25-26 (61)","until":8},{"room":"Lecture Theater C (213)","until":8},{"room":"Rm 5620, Lift 31-32 (70)","until":8}]